[
  {
    "id": 2,
    "user": "Mcfadden",
    "hotel": "MMone",
    "no_prenotation": 1218589,
    "place_of_release_document": "Winchester",
    "reservation_ps_document_type": "ID card",
    "reservation_ps_arrive_date": "2016-04-07",
    "paragraph": "Nostrud ut nostrud consectetur incididunt do sunt excepteur in. Ad laborum nostrud commodo ex anim aliqua esse labore. Commodo voluptate qui consectetur aute laborum ex minim aliquip sit ullamco. Deserunt deserunt eu id cupidatat dolore ex non minim voluptate in occaecat. Anim enim dolor consequat nisi anim ut in. Ad ipsum dolore anim cupidatat consectetur mollit deserunt.\r\n",
    "reservation_ps_leave_date": "2017-12-05",
    "no_client": 4,
    "reservation_ps_room_n": 4,
    "total_amount": "$12149"
  }
]
